{"v":"5.7.4","fr":29.9700012207031,"ip":0,"op":220.000008960784,"w":112,"h":112,"nm":"Komp 1","ddd":0,"assets":[{"id":"comp_0","layers":[{"ddd":0,"ind":1,"ty":5,"nm":"4","sr":1,"ks":{"o":{"a":0,"k":100,"ix":11},"r":{"a":0,"k":0,"ix":10},"p":{"a":0,"k":[46.5,68.5,0],"ix":2,"l":2},"a":{"a":0,"k":[0,0,0],"ix":1,"l":2},"s":{"a":0,"k":[100,100,100],"ix":6,"l":2}},"ao":0,"t":{"d":{"k":[{"s":{"s":28,"f":"Montserrat-Bold","t":"4","j":0,"tr":0,"lh":33.6,"ls":0,"fc":[0.922,0.922,0.922]},"t":0}]},"p":{},"m":{"g":1,"a":{"a":0,"k":[0,0],"ix":2}},"a":[]},"ip":0,"op":900.000036657751,"st":0,"bm":0},{"ddd":0,"ind":2,"ty":4,"nm":"Formebene 1","sr":1,"ks":{"o":{"a":0,"k":100,"ix":11},"r":{"a":0,"k":0,"ix":10},"p":{"a":0,"k":[56,56,0],"ix":2,"l":2},"a":{"a":0,"k":[0,0,0],"ix":1,"l":2},"s":{"a":0,"k":[100,100,100],"ix":6,"l":2}},"ao":0,"shapes":[{"ty":"gr","it":[{"d":1,"ty":"el","s":{"a":0,"k":[87.293,87.293],"ix":2},"p":{"a":0,"k":[0,0],"ix":3},"nm":"Elliptischer Pfad 1","mn":"ADBE Vector Shape - Ellipse","hd":false},{"ty":"fl","c":{"a":0,"k":[0.274509803922,0.305882352941,0.356862745098,1],"ix":4},"o":{"a":0,"k":100,"ix":5},"r":1,"bm":0,"nm":"Fläche 1","mn":"ADBE Vector Graphic - Fill","hd":false},{"ty":"tr","p":{"a":0,"k":[0.265,3.301],"ix":2},"a":{"a":0,"k":[0,0],"ix":1},"s":{"a":0,"k":[72.239,72.239],"ix":3},"r":{"a":0,"k":0,"ix":6},"o":{"a":0,"k":100,"ix":7},"sk":{"a":0,"k":0,"ix":4},"sa":{"a":0,"k":0,"ix":5},"nm":"Transformieren"}],"nm":"Ellipse 1","np":3,"cix":2,"bm":0,"ix":1,"mn":"ADBE Vector Group","hd":false}],"ip":0,"op":900.000036657751,"st":0,"bm":0}]}],"fonts":{"list":[{"fName":"Montserrat-Bold","fFamily":"Montserrat","fStyle":"Bold","ascent":74.1989135742188}]},"layers":[{"ddd":0,"ind":1,"ty":0,"nm":"Unterkomp. 1","refId":"comp_0","sr":1,"ks":{"o":{"a":0,"k":100,"ix":11},"r":{"a":0,"k":0,"ix":10},"p":{"a":0,"k":[56,56,0],"ix":2,"l":2},"a":{"a":0,"k":[56,56,0],"ix":1,"l":2},"s":{"a":1,"k":[{"i":{"x":[0.833,0.833,0.833],"y":[0.833,0.833,0.833]},"o":{"x":[0.167,0.167,0.167],"y":[0.167,0.167,0.167]},"t":0,"s":[100,100,100]},{"i":{"x":[0.833,0.833,0.833],"y":[0.833,0.833,0.833]},"o":{"x":[0.167,0.167,0.167],"y":[0.167,0.167,0.167]},"t":11,"s":[118,118,100]},{"t":23.0000009368092,"s":[100,100,100]}],"ix":6,"l":2}},"ao":0,"w":112,"h":112,"ip":0,"op":900.000036657751,"st":0,"bm":0}],"markers":[],"chars":[{"ch":"4","size":28,"style":"Bold","w":68.9,"data":{"shapes":[{"ty":"gr","it":[{"ind":0,"ty":"sh","ix":1,"ks":{"a":0,"k":{"i":[[0,0],[0,0],[0,0],[0,0],[0,0],[0,0],[0,0],[0,0],[0,0],[0,0],[0,0],[0,0],[0,0],[0,0],[0,0]],"o":[[0,0],[0,0],[0,0],[0,0],[0,0],[0,0],[0,0],[0,0],[0,0],[0,0],[0,0],[0,0],[0,0],[0,0],[0,0]],"v":[[68.481,-28.098],[57.001,-28.098],[57.001,-41.29],[41.592,-41.29],[41.592,-28.098],[22.659,-28.098],[53.476,-70.496],[36.356,-70.496],[3.122,-25.781],[3.122,-14.804],[41.089,-14.804],[41.089,0],[57.001,0],[57.001,-14.804],[68.481,-14.804]],"c":true},"ix":2},"nm":"4","mn":"ADBE Vector Shape - Group","hd":false}],"nm":"4","np":3,"cix":2,"bm":0,"ix":1,"mn":"ADBE Vector Group","hd":false}]},"fFamily":"Montserrat"}]}